{
    "Mexico": "México",
    "South Africa": "África do Sul",
    "South Korea": "Coreia do Sul",
    "Canada": "Canadá",
    "Qatar": "Catar",
    "Switzerland": "Suíça",
    "Brazil": "Brasil",
    "Morocco": "Marrocos",
    "Haiti": "Haiti",
    "Scotland": "Escócia",
    "USA": "Estados Unidos",
    "Paraguay": "Paraguai",
    "Australia": "Austrália",
    "Germany": "Alemanha",
    "Curaçao": "Curaçau",
    "Côte d'Ivoire": "Costa do Marfim",
    "Ecuador": "Equador",
    "Netherlands": "Holanda",
    "Japan": "Japão",
    "Tunisia": "Tunísia",
    "Belgium": "Bélgica",
    "Egypt": "Egito",
    "IR Iran": "Irã",
    "New Zealand": "Nova Zelândia",
    "Spain": "Espanha",
    "Cabo Verde": "Cabo Verde",
    "Saudi Arabia": "Arábia Saudita",
    "Uruguay": "Uruguai",
    "France": "França",
    "Senegal": "Senegal",
    "Norway": "Noruega",
    "Argentina": "Argentina",
    "Algeria": "Argélia",
    "Austria": "Áustria",
    "Jordan": "Jordânia",
    "Portugal": "Portugal",
    "Uzbekistan": "Uzbequistão",
    "Colombia": "Colômbia",
    "England": "Inglaterra",
    "Croatia": "Croácia",
    "Ghana": "Gana",
    "Panama": "Panamá",
    "Winner UEFA Playoff D": "Vencedor Repescagem UEFA D",
    "Winner UEFA Playoff A": "Vencedor Repescagem UEFA A",
    "Winner UEFA Playoff C": "Vencedor Repescagem UEFA C",
    "Winner UEFA Playoff B": "Vencedor Repescagem UEFA B",
    "Winner FIFA Playoff 1": "Vencedor Repescagem FIFA 1",
    "Winner FIFA Playoff 2": "Vencedor Repescagem FIFA 2"
}
